pypollinations/__init__.py
pypollinations/client/__init__.py
pypollinations/client/base.py
pypollinations/client/image.py
pypollinations/client/text.py
pypollinations/exceptions.py
pypollinations/models/__init__.py
pypollinations/models/base.py
pypollinations/models/image.py
pypollinations/models/text.py
pypollinations/utils.py
pypollinations-0.2.0.dist-info/LICENSE
pypollinations-0.2.0.dist-info/METADATA
pypollinations-0.2.0.dist-info/WHEEL
pypollinations-0.2.0.dist-info/RECORD
