Metadata-Version: 2.1
Name: pypollinations
Version: 0.2.0
Summary: Python client for Pollinations AI API
License: Apache-2.0
Author: Krishnatejaswi S
Requires-Python: >=3.10,<4.0
Classifier: License :: OSI Approved :: Apache Software License
Classifier: Programming Language :: Python :: 3
Classifier: Programming Language :: Python :: 3.10
Classifier: Programming Language :: Python :: 3.11
Classifier: Programming Language :: Python :: 3.12
Classifier: Programming Language :: Python :: 3.13
Requires-Dist: httpx (>=0.28.1,<0.29.0)
Requires-Dist: pillow (>=11.0.0,<12.0.0)
Requires-Dist: pydantic (>=2.10.3,<3.0.0)
Requires-Dist: requests (>=2.32.3,<3.0.0)
